_updateversion.py
tofu_helpers/__init__.py
tofu_helpers/openmp_helpers.py
tofu.libs/libgomp-f7e03b3e.so.1.0.0
tofu-1.7.0.dist-info/WHEEL
tofu-1.7.0.dist-info/entry_points.txt
tofu-1.7.0.dist-info/top_level.txt
tofu-1.7.0.dist-info/LICENSE.txt
tofu-1.7.0.dist-info/RECORD
tofu-1.7.0.dist-info/METADATA
inputs_temp/dlines.py
inputs_temp/__init__.py
inputs_temp/XICS_allshots_C34.py
tofu/_physics.py
tofu/utils.py
tofu/__init__.py
tofu/defaults.py
tofu/version.py
tofu/pathfile.py
tofu/_plot.py
tofu/imas2tofu/_comp_toobjects.py
tofu/imas2tofu/_comp.py
tofu/imas2tofu/_core.py
tofu/imas2tofu/_comp_mesh.py
tofu/imas2tofu/__init__.py
tofu/imas2tofu/_def.py
tofu/imas2tofu/_mat2ids2calc.py
tofu/benchmarks/benchmarks_01_Mesh2D_peakmem.py
tofu/benchmarks/benchmarks_01_Mesh2D_time.py
tofu/benchmarks/benchmarks_02_spectralfit_peakmem.py
tofu/benchmarks/__init__.py
tofu/benchmarks/benchmarks_02_spectralfit_time.py
tofu/benchmarks/benchmarks_00_Geometry_peakmem.py
tofu/benchmarks/benchmarks_00_Geometry_time.py
tofu/benchmarks/benchmarks_03_solidangles.py
tofu/dust/_comp.py
tofu/dust/_core.py
tofu/dust/__init__.py
tofu/dust/_plot.py
tofu/mag/test_magFieldLines.py
tofu/mag/regression_test.py
tofu/mag/__init__.py
tofu/mag/equimap.py
tofu/mag/test_equimap.py
tofu/mag/test_ripple.py
tofu/mag/magFieldLines.py
tofu/mag/mag_ripple/mag_ripple.f
tofu/mag/mag_ripple/__init__.py
tofu/mag/mag_ripple/compile_f2py.sh
tofu/tomotok2tofu/_core.py
tofu/tomotok2tofu/__init__.py
tofu/entrypoints/tofucalc.py
tofu/entrypoints/__init__.py
tofu/entrypoints/_def.py
tofu/entrypoints/tofuplot.py
tofu/geom/_basic_geom_tools.pxd
tofu/geom/_chained_list.cpython-37m-x86_64-linux-gnu.so
tofu/geom/_distance_tools.cpython-37m-x86_64-linux-gnu.so
tofu/geom/_vignetting_tools.pyx
tofu/geom/_core_optics.py
tofu/geom/_sampling_tools.cpython-37m-x86_64-linux-gnu.so
tofu/geom/_comp.py
tofu/geom/_distance_tools.pxd
tofu/geom/_comp_optics.py
tofu/geom/_raytracing_tools.pxd
tofu/geom/_raytracing_tools.pyx
tofu/geom/_basic_geom_tools.pyx
tofu/geom/_check_optics.py
tofu/geom/_core.py
tofu/geom/_GG.cpython-37m-x86_64-linux-gnu.so
