Metadata-Version: 2.1
Name: tofu
Version: 1.7.0
Summary: A python library for Tomography for Fusion
Home-page: https://github.com/ToFuProject/tofu
Author: Didier VEZINET and Laura MENDOZA
Author-email: didier.vezinet@gmail.com
License: MIT
Keywords: tomography geometry 3D inversion synthetic fusion
Classifier: Development Status :: 4 - Beta
Classifier: Intended Audience :: Science/Research
Classifier: Topic :: Scientific/Engineering :: Physics
Classifier: License :: OSI Approved :: MIT License
Classifier: Programming Language :: Python :: 3.6
Classifier: Programming Language :: Python :: 3.7
Classifier: Natural Language :: English
Requires-Python: >=3.6
License-File: LICENSE.txt
Requires-Dist: numpy
Requires-Dist: scipy
Requires-Dist: matplotlib (<=3.5.2)
Requires-Dist: contourpy
Requires-Dist: requests
Requires-Dist: svg.path
Requires-Dist: Polygon3
Requires-Dist: cython (>=0.26)
Requires-Dist: bsplines2d (>=0.0.2)
Provides-Extra: dev
Requires-Dist: check-manifest ; extra == 'dev'
Requires-Dist: coverage ; extra == 'dev'
Requires-Dist: pytest ; extra == 'dev'
Requires-Dist: sphinx ; extra == 'dev'
Requires-Dist: sphinx-gallery ; extra == 'dev'
Requires-Dist: sphinx-bootstrap-theme ; extra == 'dev'
